my_loc/__init__.py
myloc-1.1.2.dist-info/METADATA
myloc-1.1.2.dist-info/WHEEL
myloc-1.1.2.dist-info/top_level.txt
myloc-1.1.2.dist-info/RECORD
