Metadata-Version: 2.1
Name: myloc
Version: 1.1.2
Summary: A python package to get the location.
Home-page: https://github.com/PIYUSH-GEEK/myloc
Author: Piyush Kumar
Author-email: pk33463@gmail.com
License: UNKNOWN
Platform: UNKNOWN
Classifier: Programming Language :: Python :: 3
Classifier: Programming Language :: Python :: 3.7
Classifier: License :: OSI Approved :: MIT License
Classifier: Operating System :: OS Independent
Requires-Dist: requests
Requires-Dist: bs4
